LPV/__init__.py
LPV/src/ast.py
LPV/src/error.py
LPV/src/lexer.py
LPV/src/parser.py
LPV/src/token.py
LPV/tools/prettier.py
LPV-2.2.dist-info/METADATA
LPV-2.2.dist-info/WHEEL
LPV-2.2.dist-info/top_level.txt
LPV-2.2.dist-info/RECORD
