Metadata-Version: 2.1
Name: LPV
Version: 2.2
Summary: Fast Parser Library
Home-page: https://github.com/Xp-op/LPV
Author: Xp-op
Author-email: muhammad184276@gmail.com
License: UNKNOWN
Project-URL: Bug Tracker, https://github.com/Xp-op/LPV/issues
Platform: UNKNOWN
Classifier: Programming Language :: Python :: 3
Classifier: License :: OSI Approved :: MIT License
Classifier: Operating System :: OS Independent
Requires-Python: >=3.6
